dlt_source_affinity/__init__.py
dlt_source_affinity/helpers.py
dlt_source_affinity/rest_client.py
dlt_source_affinity/settings.py
dlt_source_affinity/type_adapters.py
dlt_source_affinity/model/.gitattributes
dlt_source_affinity/model/__init__.py
dlt_source_affinity/model/v1.py
dlt_source_affinity/model/v2/__init__.py
dlt_source_affinity/model/v2/interactions.py
dlt_source_affinity/model/v2/notes.py
dlt_source_affinity-0.1.20.dist-info/METADATA
dlt_source_affinity-0.1.20.dist-info/WHEEL
dlt_source_affinity-0.1.20.dist-info/licenses/LICENSE
dlt_source_affinity-0.1.20.dist-info/RECORD
