Metadata-Version: 2.4
Name: dlt-source-affinity
Version: 0.1.20
Summary: A DLT source for the Affinity CRM
License: MIT
License-File: LICENSE
Classifier: Intended Audience :: Developers
Classifier: License :: OSI Approved :: MIT License
Classifier: Operating System :: OS Independent
Classifier: Programming Language :: Python :: 3
Classifier: Programming Language :: Python :: 3.12
Classifier: Topic :: Software Development :: Libraries
Requires-Python: >=3.12
Requires-Dist: dlt>=1.17.1
Requires-Dist: pydantic-flatten-rootmodel>=0.1.2
Provides-Extra: show
Requires-Dist: dlt[duckdb]>=1.17.1; extra == 'show'
Requires-Dist: dlt[workspace]>=1.17.1; extra == 'show'
Requires-Dist: streamlit>=1.41.1; extra == 'show'
Requires-Dist: watchdog>=6.0.0; extra == 'show'
